fds/__init__.py
fds/sdk/__init__.py
fds/sdk/ModelPortfolio/__init__.py
fds/sdk/ModelPortfolio/api_client.py
fds/sdk/ModelPortfolio/configuration.py
fds/sdk/ModelPortfolio/exceptions.py
fds/sdk/ModelPortfolio/model_utils.py
fds/sdk/ModelPortfolio/rest.py
fds/sdk/ModelPortfolio/api/__init__.py
fds/sdk/ModelPortfolio/api/model_accounts_api.py
fds/sdk/ModelPortfolio/apis/__init__.py
fds/sdk/ModelPortfolio/model/__init__.py
fds/sdk/ModelPortfolio/model/model_account_additional_field.py
fds/sdk/ModelPortfolio/model/model_account_fields.py
fds/sdk/ModelPortfolio/model/model_account_fields_root.py
fds/sdk/ModelPortfolio/model/problem_details.py
fds/sdk/ModelPortfolio/models/__init__.py
fds.sdk.ModelPortfolio-0.21.1.dist-info/LICENSE
fds.sdk.ModelPortfolio-0.21.1.dist-info/METADATA
fds.sdk.ModelPortfolio-0.21.1.dist-info/WHEEL
fds.sdk.ModelPortfolio-0.21.1.dist-info/top_level.txt
fds.sdk.ModelPortfolio-0.21.1.dist-info/RECORD
